encrypted/inference/eibase/__init__.py
encrypted/inference/eiclient/__init__.py
encrypted/inference/eiserver/__init__.py
encrypted/inference/internal/__init__.py
encrypted/inference/internal/_version.py
encrypted/inference/internal/einative.py
encrypted/inference/internal/eiutils.py
encrypted/inference/internal/parameters.json
encrypted_inference-0.9.dist-info/LICENSE
encrypted_inference-0.9.dist-info/METADATA
encrypted_inference-0.9.dist-info/WHEEL
encrypted_inference-0.9.dist-info/top_level.txt
encrypted_inference-0.9.dist-info/RECORD
