Metadata-Version: 2.1
Name: encrypted-inference
Version: 0.9
Summary: SDK for calling/providing an encrypted inference service
Home-page: https://sealcrypto.org
Author: Microsoft Research
Author-email: sealcrypto@microsoft.com
License: MIT
Platform: UNKNOWN
Classifier: Programming Language :: Python :: 3
Classifier: License :: OSI Approved :: MIT License
Classifier: Operating System :: POSIX :: Linux
Classifier: Operating System :: Microsoft :: Windows
Requires-Dist: numpy
